copyparty/__init__.py
copyparty/__main__.py
copyparty/__version__.py
copyparty/authsrv.py
copyparty/broker_mp.py
copyparty/broker_mpw.py
copyparty/broker_thr.py
copyparty/broker_util.py
copyparty/cert.py
copyparty/cfg.py
copyparty/dxml.py
copyparty/fsutil.py
copyparty/ftpd.py
copyparty/httpcli.py
copyparty/httpconn.py
copyparty/httpsrv.py
copyparty/ico.py
copyparty/mdns.py
copyparty/metrics.py
copyparty/mtag.py
copyparty/multicast.py
copyparty/pwhash.py
copyparty/qrkode.py
copyparty/sftpd.py
copyparty/smbd.py
copyparty/ssdp.py
copyparty/star.py
copyparty/sutil.py
copyparty/svchub.py
copyparty/szip.py
copyparty/tcpsrv.py
copyparty/tftpd.py
copyparty/th_cli.py
copyparty/th_srv.py
copyparty/u2idx.py
copyparty/up2k.py
copyparty/util.py
copyparty/bos/__init__.py
copyparty/bos/bos.py
copyparty/bos/path.py
copyparty/res/COPYING.txt
copyparty/res/__init__.py
copyparty/res/insecure.pem
copyparty/stolen/__init__.py
copyparty/stolen/qrcodegen.py
copyparty/stolen/surrogateescape.py
copyparty/stolen/dnslib/__init__.py
copyparty/stolen/dnslib/bimap.py
copyparty/stolen/dnslib/bit.py
copyparty/stolen/dnslib/buffer.py
copyparty/stolen/dnslib/dns.py
copyparty/stolen/dnslib/label.py
copyparty/stolen/dnslib/lex.py
copyparty/stolen/dnslib/ranges.py
copyparty/stolen/ifaddr/__init__.py
copyparty/stolen/ifaddr/_posix.py
copyparty/stolen/ifaddr/_shared.py
copyparty/stolen/ifaddr/_win32.py
copyparty/web/baguettebox.js.gz
copyparty/web/browser.css.gz
copyparty/web/browser.html
copyparty/web/browser.js.gz
copyparty/web/browser2.html
copyparty/web/cf.html
copyparty/web/dbg-audio.js.gz
copyparty/web/idp.html
copyparty/web/md.css.gz
copyparty/web/md.html
copyparty/web/md.js.gz
copyparty/web/md2.css.gz
copyparty/web/md2.js.gz
copyparty/web/mde.css.gz
copyparty/web/mde.html
copyparty/web/mde.js.gz
copyparty/web/msg.html
copyparty/web/opds.xml
copyparty/web/rups.css.gz
copyparty/web/rups.html
copyparty/web/rups.js.gz
copyparty/web/shares.css.gz
copyparty/web/shares.html
copyparty/web/shares.js.gz
copyparty-1.20.6.dist-info/licenses/LICENSE
copyparty-1.20.6.dist-info/METADATA
copyparty-1.20.6.dist-info/WHEEL
copyparty-1.20.6.dist-info/entry_points.txt
copyparty-1.20.6.dist-info/top_level.txt
copyparty-1.20.6.dist-info/RECORD
