Metadata-Version: 2.4
Name: copyparty
Version: 1.20.6
Summary:   Portable file server with accelerated resumable uploads, deduplication, WebDAV, SFTP, FTP, zeroconf, media indexer, video thumbnails, audio transcoding, and write-only folders
Author-email: ed <copyparty@ocv.me>
License: MIT
Project-URL: Source Code, https://github.com/9001/copyparty
Project-URL: Bug Tracker, https://github.com/9001/copyparty/issues
Project-URL: Demo Server, https://a.ocv.me/pub/demo/
Classifier: Development Status :: 5 - Production/Stable
Classifier: License :: OSI Approved :: MIT License
Classifier: Programming Language :: Python
Classifier: Programming Language :: Python :: 3
Classifier: Programming Language :: Python :: 3.3
Classifier: Programming Language :: Python :: 3.4
Classifier: Programming Language :: Python :: 3.5
Classifier: Programming Language :: Python :: 3.6
Classifier: Programming Language :: Python :: 3.7
Classifier: Programming Language :: Python :: 3.8
Classifier: Programming Language :: Python :: 3.9
Classifier: Programming Language :: Python :: 3.10
Classifier: Programming Language :: Python :: 3.11
Classifier: Programming Language :: Python :: 3.12
Classifier: Programming Language :: Python :: 3.13
Classifier: Programming Language :: Python :: Implementation :: CPython
Classifier: Programming Language :: Python :: Implementation :: Jython
Classifier: Programming Language :: Python :: Implementation :: PyPy
Classifier: Operating System :: OS Independent
Classifier: Environment :: Console
Classifier: Environment :: No Input/Output (Daemon)
Classifier: Intended Audience :: End Users/Desktop
Classifier: Intended Audience :: System Administrators
Classifier: Topic :: Communications :: File Sharing
Classifier: Topic :: Internet :: File Transfer Protocol (FTP)
Classifier: Topic :: Internet :: WWW/HTTP :: HTTP Servers
Requires-Python: >=3.3
License-File: LICENSE
Requires-Dist: Jinja2
Provides-Extra: all
Requires-Dist: argon2-cffi; extra == "all"
Requires-Dist: paramiko; extra == "all"
Requires-Dist: partftpy>=0.4.0; extra == "all"
Requires-Dist: Pillow; extra == "all"
Requires-Dist: pyftpdlib; extra == "all"
Requires-Dist: pyopenssl; extra == "all"
Requires-Dist: pyzmq; extra == "all"
Provides-Extra: thumbnails
Requires-Dist: Pillow; extra == "thumbnails"
Provides-Extra: thumbnails2
Requires-Dist: pyvips; extra == "thumbnails2"
Provides-Extra: audiotags
Requires-Dist: mutagen; extra == "audiotags"
Provides-Extra: sftp
Requires-Dist: paramiko; extra == "sftp"
Provides-Extra: ftpd
Requires-Dist: pyftpdlib; extra == "ftpd"
Provides-Extra: ftps
Requires-Dist: pyftpdlib; extra == "ftps"
Requires-Dist: pyopenssl; extra == "ftps"
Provides-Extra: tftpd
Requires-Dist: partftpy>=0.4.0; extra == "tftpd"
Provides-Extra: pwhash
Requires-Dist: argon2-cffi; extra == "pwhash"
Provides-Extra: zeromq
Requires-Dist: pyzmq; extra == "zeromq"
Dynamic: license-file
